<keymap version="1" name="Default copy" parent="Default for XWin">
  <action id="ActivateRunToolWindow" />
  <action id="EditorAddOrRemoveCaret">
    <mouse-shortcut keystroke="alt button1" />
    <mouse-shortcut keystroke="shift button1" />
  </action>
  <action id="GotoSymbol">
    <keyboard-shortcut first-keystroke="alt s" />
  </action>
  <action id="GotoTest" />
  <action id="Images.ShowThumbnails" />
  <action id="OptimizeImports">
    <keyboard-shortcut first-keystroke="ctrl alt o" />
    <keyboard-shortcut first-keystroke="alt i" />
  </action>
  <action id="ReformatCode">
    <keyboard-shortcut first-keystroke="ctrl alt l" />
    <keyboard-shortcut first-keystroke="alt f" />
  </action>
  <action id="Refresh" />
  <action id="Rerun">
    <keyboard-shortcut first-keystroke="shift alt t" />
  </action>
  <action id="RunClass">
    <keyboard-shortcut first-keystroke="shift ctrl f10" />
    <keyboard-shortcut first-keystroke="alt t" />
  </action>
  <action id="SwitchApply">
    <keyboard-shortcut first-keystroke="shift alt enter" />
  </action>
  <action id="SwitchDown">
    <keyboard-shortcut first-keystroke="shift alt down" />
  </action>
  <action id="SwitchLeft">
    <keyboard-shortcut first-keystroke="shift alt left" />
  </action>
  <action id="SwitchRight">
    <keyboard-shortcut first-keystroke="shift alt right" />
  </action>
  <action id="SwitchUp">
    <keyboard-shortcut first-keystroke="shift alt up" />
  </action>
  <action id="Vcs.UpdateProject" />
  <action id="tasks.switch" />
  <action id="tasks.switch.toolbar" />
</keymap>